README.rst
setup.py
docker_ps/__init__.py
docker_ps.egg-info/PKG-INFO
docker_ps.egg-info/SOURCES.txt
docker_ps.egg-info/dependency_links.txt
docker_ps.egg-info/entry_points.txt
docker_ps.egg-info/requires.txt
docker_ps.egg-info/top_level.txt