Metadata-Version: 1.1
Name: docker-ps
Version: 0.1.3
Summary: Simplify docker-ps output
Home-page: https://github.com/iamfat/docker-ps
Author: Jia Huang
Author-email: iamfat@gmail.com
License: MIT
Keywords: d,o,c,k,e,r, ,p,a,r,s,e, ,r,u,n, ,o,p,t,i,o,n,s
Platform: UNKNOWN
Classifier: Development Status :: 3 - Alpha
Classifier: Intended Audience :: Developers
Classifier: Topic :: Utilities
Classifier: License :: OSI Approved :: MIT License
